Workbook

Sheet RACI
A1: Function | B1: Activity | C1: AC | D1: DI | E1: AB | F1: NI | G1: OPS | H1: PDS | I1: SS | J1: KL | K1: EH | L1: IT | M1: JH | N1: PC | O1: PR | P1: IF | Q1: CH | R1: WI | S1: TK | T1: CI | U1: Transitions to | V1: Source | W1: Notes
C2: Ayesha Curry | D2: Danielle Iturbe | E2: Alvin Belt | F2: Nicole Iturbe | G2: OPEN | H2: OPEN | I2: Soraya Salgadoe | J2: Kate Le | K2: Erin Hover | L2: Ivy Tan | M2: Jan Haeck | N2: Perrine Calvet | O2: Pedrero Regulatory | P2: Ironclad Finance | Q2: Calm HR | R2: WITHIN | S2: Teknologics | T2: Coastal Interactive
A3: Product Development | B3: Formula stage-gate progression through the PD Formula Tracker | D3: I | E3: R | F3: C | H3: -> | I3: I | N3: A | U3: Product Development Specialist | V3: .claude/skills/asana-pd-manager/references/role-map.md:16; .claude/skills/asana-pd-manager/SKILL.md:60; Alvin, 2026-07-31 (Coastal Interactive; PD visibility) | W3: PD Lead holds technical sign-off on formula stage moves. Operator confirms every move (Rule 1 preview); reversals get a stronger intent check. Perrine and Soraya are never blank on a PD row - PD technical guidance and the marketing read both need visibility on every product decision.
A4: Product Development | B4: Compatibility, stability, RIPT and PET decisions (pre-launch) | E4: C | F4: I | I4: I | N4: A/R | V4: .claude/skills/asana-pd-manager/references/role-map.md:16; Alvin, 2026-07-31 (Coastal Interactive; PD visibility) | W4: PD Lead owns the technical call outright. A and R the same person, and PC is an external contractor. Perrine and Soraya are never blank on a PD row - PD technical guidance and the marketing read both need visibility on every product decision.
A5: Product Development | B5: Packaging development with fillers and component vendors | C5: I | D5: I | E5: C | I5: I | K5: A | L5: C | M5: R | N5: C | V5: .claude/skills/asana-pd-manager/references/role-map.md:16,23; Alvin, 2026-07-31 (role correction); Alvin, 2026-07-31 (Coastal Interactive; PD visibility) | W5: PD Lead owns packaging dev calls; Jan executes packaging and artwork under Erin. Both are contractors. Erin is the lead technical authority on packaging and artwork and answers for the outcome; Jan executes under her. Perrine consults where formula contact or compatibility is in play. Both Erin and Jan are contractors. Perrine and Soraya are never blank on a PD row - PD technical guidance and the marketing read both need visibility on every product decision.
A6: Product Development | B6: Direction-changing PD decisions (launch scope, supplier change, kill calls) | C6: I | D6: A | E6: R | F6: C | I6: I | N6: C | V6: .claude/skills/asana-pd-manager/references/role-map.md:17,18; Alvin, 2026-07-31 (Coastal Interactive; PD visibility) | W6: President approves. PD Consult is final-line approver alongside the President. Perrine and Soraya are never blank on a PD row - PD technical guidance and the marketing read both need visibility on every product decision.
A7: Product Development | B7: Founder approval on brand-line moves | C7: A | D7: C | E7: R | F7: C | I7: I | N7: I | V7: .claude/skills/asana-pd-manager/references/role-map.md:19; Alvin, 2026-07-31 (Coastal Interactive; PD visibility) | W7: Founder gate. Ayesha receives weekly PD signal through the Friday briefing. Perrine and Soraya are never blank on a PD row - PD technical guidance and the marketing read both need visibility on every product decision.
A8: Product Development | B8: PD signal intake from meetings and supplier email, plus PD status reporting | D8: I | E8: A/R | F8: C | H8: -> | I8: I | N8: C | U8: Product Development Specialist | V8: .claude/skills/fireflies-asana-bridge/SKILL.md:287; .claude/skills/outlook-plm-bridge/SKILL.md:191; .claude/skills/sjs-status-reporter/SKILL.md:331,385; Alvin, 2026-07-31 (Coastal Interactive; PD visibility) | W8: Alvin is the named approver on Flow D formula-approval decisions and classifies every meeting item. Covers the three PD hub dashboards. A and R both AB. Perrine and Soraya are never blank on a PD row - PD technical guidance and the marketing read both need visibility on every product decision.
A9: Product Development | B9: Reformulation triggered by a Quality or Regulatory reverse-handoff | D9: I | E9: R | F9: C | I9: I | N9: A | V9: .claude/skills/asana-pd-manager/references/role-map.md:16; .claude/skills/capa-coordinator/SKILL.md:85; Alvin, 2026-07-31 (Coastal Interactive; PD visibility) | W9: PD Lead is cross-flagged for any PD-side reformulation. Reformulation handoff rides the root-cause approval - no separate gate. Perrine and Soraya are never blank on a PD row - PD technical guidance and the marketing read both need visibility on every product decision.
A10: Product Development | B10: Document control: specifications, dielines, artwork versions, BOMs, landed-cost integrity | E10: R | F10: A | H10: -> | I10: I | K10: C | M10: C | N10: C | U10: Product Development Specialist | V10: SharePoint: Sweet July Skin - Product Development Specialist - Job Description.docx; Alvin, 2026-07-31 (Coastal Interactive; PD visibility) | W10: Documentation quality is Nicole's gate. The PD Specialist JD names document control as a core responsibility, so this row transitions on hire. Perrine and Soraya are never blank on a PD row - PD technical guidance and the marketing read both need visibility on every product decision.
A11: Operations & Supply Chain | B11: Vendor master data, onboarding (NDA + W9 gate), sourcing and performance scorecards | E11: A/R | F11: C | G11: -> | I11: C | N11: C | U11: Operations Specialist | V11: .claude/skills/purchasing-manager/SKILL.md:42,46,75,154,158 | W11: PLM vendor record created only after Operations approves at 2D. First-contact routing varies by vendor_type (SKILL.md:50-56) but the approval gate does not. A and R both AB.
A12: Operations & Supply Chain | B12: Purchase order lifecycle: placement, acknowledgement variance, close and discrepancy | E12: A/R | G12: -> | N12: C | U12: Operations Specialist | V12: .claude/skills/purchasing-manager/SKILL.md:108,116,140,248 | W12: Six sub-flows from draft to close, plus Job 10 discrepancy investigation. Every gate is Operations. A and R both AB.
A13: Operations & Supply Chain | B13: Goods receipt on PD-linked purchase orders | E13: R | F13: C | N13: A | V13: .claude/skills/purchasing-manager/SKILL.md:130 | W13: PD owns the close on PD-linked receipts; Purchasing carries the receipt signal only. The one Ops row where accountability sits off the VP seat.
A14: Operations & Supply Chain | B14: Three-way reconciliation across PLM, Shopify and Logiwa | E14: A/R | F14: C | G14: -> | U14: Operations Specialist | V14: .claude/skills/inventory-manager/SKILL.md:68 | W14: Operations decides the correction direction, usually trusting Logiwa as physical reality. A and R both AB.
A15: Operations & Supply Chain | B15: Vendor invoice classification and cost capture (five HITL gates) | D15: I | E15: A/R | F15: C | G15: -> | I15: C | P15: C | U15: Operations Specialist | V15: .claude/skills/purchasing-manager/SKILL.md:234,235,238; Alvin, 2026-07-31 (external partners) | W15: Operator confirms cost_category, regulatory_driver, linked SKU and multi-home routing before any PLM write, and approves the dispute branch. A and R both AB. Ironclad consulted - classified invoices land in their ledger.
A16: Operations & Supply Chain | B16: Inventory position keeping, batch creation on receipt and the location ledger | E16: A/R | F16: I | G16: -> | N16: C | U16: Operations Specialist | V16: .claude/skills/inventory-manager/SKILL.md:18,52,60 | W16: Ex-Ops-Coordinator scope. Alvin took inventory under the 2026-07-17 interim split. A and R both AB.
A17: Operations & Supply Chain | B17: Adjustments, write-offs and return dispositions | E17: A/R | G17: -> | N17: C | U17: Operations Specialist | V17: .claude/skills/inventory-manager/SKILL.md:94 | W17: Operations approves. Near-expiry write-offs wait on the quality call first. A and R both AB.
A18: Operations & Supply Chain | B18: S&OP: forecast, inventory targets and buy recommendations | D18: I | E18: A/R | F18: C | G18: -> | U18: Operations Specialist | V18: .claude/skills/supply-demand-planner/SKILL.md:30-52; .claude/skills/supply-demand-planner/references/plm-schema-additions.md:139 | W18: Operations approves; plm-assistant executes the SQL. Four intertwined jobs on one person. A and R both AB.
A19: Operations & Supply Chain | B19: Inbound freight, customs, duty and carrier claims | E19: A/R | G19: -> | N19: I | U19: Operations Specialist | V19: .claude/skills/logistics-manager/SKILL.md:59,186; .claude/skills/logistics-manager/forms/international-dtc-shipment.md:11 | W19: Nothing created or updated until Operations signs off. Ex-Ops-Coordinator logistics scope, now Alvin. HCT and Impress origin Asia so customs is routine. A and R both AB.
A20: Operations & Supply Chain | B20: Daily DTC order operations and the Logiwa report parse | E20: C | F20: A/R | G20: -> | U20: Operations Specialist | V20: .claude/skills/ayesha-weekly-briefing/SKILL.md:123; .claude/skills/oc3pl-order-manager/SKILL.md:109,191 | W20: Ex-Ops-Coordinator scope. Nicole covers order management and OC3PL under the 2026-07-17 interim split. A and R both NI.
A21: Operations & Supply Chain | B21: Pre-ship out-of-stock holds from the shortage sheet | E21: R | F21: A | G21: -> | U21: Operations Specialist | V21: .claude/skills/oc3pl-order-manager/SKILL.md:201; .claude/skills/ayesha-weekly-briefing/SKILL.md:123 | W21: Order-side holds sit with Nicole; SKU-level shortage routing belongs to inventory-manager, so Alvin does the work.
A22: Operations & Supply Chain | B22: Retailer ASN / EDI 856 and routing-guide compliance (Ulta DC, Amazon Vendor) | D22: I | E22: R | F22: A | G22: -> | U22: Operations Specialist | V22: .claude/skills/logistics-manager/SKILL.md:80; .claude/skills/purchasing-manager/SKILL.md:55 | W22: Operations or Order Ops reviews. UBM launch June 2026 is the deadline driver on this lane.
A23: Operations & Supply Chain | B23: Production scheduling with manufacturing partners | E23: A/R | F23: C | G23: -> | N23: C | U23: Operations Specialist | V23: SharePoint: Sweet July Skin - Operations Specialist - Job Description.docx; Leadership Business Review 2026-07-30 35:18 | W23: Named in the Ops Specialist JD under Planning & Special Projects. Today Alvin coordinates KDC scheduling directly. A and R both AB until the seat is filled.
A24: Quality | B24: Customer complaint intake, classification and first response | E24: R | F24: A | H24: -> | N24: C | U24: Product Development Specialist | V24: .claude/skills/complaint-and-event-handler/SKILL.md:20,53 | W24: HITL on every write. Operator approves classification plus first response. A and R both AB. Gate moved to Nicole as the final quality check per Leadership Business Review 2026-07-30 25:18-26:01.
A25: Quality | B25: Complaint trend analysis by SKU and batch | E25: R | F25: A | H25: -> | N25: C | U25: Product Development Specialist | V25: .claude/skills/quality-manager/references/role-map.md:15 | W25: Voice of Customer holds gates on complaint classification and complaint-driven escalations. Nicole already held this gate; monthly trend review formalizes it per Leadership Business Review 2026-07-30 26:02-26:17.
A26: Quality | B26: NCR and CAPA lifecycle, intake through close (SKN-OPS-001) | D26: I | E26: R | F26: A | H26: -> | N26: C | U26: Product Development Specialist | V26: .claude/skills/capa-coordinator/SKILL.md:54,136; .claude/skills/capa-coordinator/references/ncr-procedure.md:135; .claude/skills/capa-coordinator/references/skn-ops-001.md:64,102 | W26: Operator approves intake and both action plans; QA Lead approves conversion, root cause, verification, effectiveness and close. Six SOP phases, one external contractor on every technical gate. A moved from Perrine to Nicole per Leadership Business Review 2026-07-30 25:18-25:50. Perrine consults on technical root cause.
A27: Quality | B27: Lab finding intake and OOS / OOT classification (SKN-OPS-006) | E27: R | F27: A | H27: -> | N27: C | U27: Product Development Specialist | V27: .claude/skills/quality-lab-coordinator/SKILL.md:48,56 | W27: Operator approves intake and the single-versus-systemic classification. A and R both AB. Gate moved to Nicole per Leadership Business Review 2026-07-30 25:35-25:50. Perrine consults on the technical call.
A28: Quality | B28: Vendor quality flag and scorecard signal back to Purchasing | E28: R | F28: A | H28: -> | N28: C | U28: Product Development Specialist | V28: .claude/skills/quality-lab-coordinator/SKILL.md:76; .claude/skills/quality-lab-coordinator/references/vendor-scorecard-signal.md:103 | W28: QA Lead approves any vendor flag and the scorecard band. Operator can stage but not commit. A moved from Perrine to Nicole per Leadership Business Review 2026-07-30 25:18-25:50. Perrine consults.
A29: Quality | B29: Batch hold and release (SKN-OPS-007) | D29: I | E29: R | F29: A | H29: -> | N29: C | U29: Product Development Specialist | V29: .claude/skills/batch-lifecycle-tracker/references/batch-lifecycle-procedure.md:208; .claude/skills/batch-lifecycle-tracker/SKILL.md:86 | W29: QA Lead approves every hold and every release. No exceptions at v5.4. Releases need a CAPA close or clean retest plus QA Lead judgment. A moved from Perrine to Nicole per Leadership Business Review 2026-07-30 25:35-26:01. Perrine consults on the technical basis.
A30: Quality | B30: In-market stability testing decisions (PET, accelerated, real-time) | E30: R | F30: C | H30: -> | N30: A | U30: Product Development Specialist | V30: .claude/skills/batch-lifecycle-tracker/SKILL.md:71,94 | W30: Technical testing call stays with Perrine as the R&D and quality technical advisor. Operator approves schedule edits. Per Leadership Business Review 2026-07-30 25:18-25:35 the process gate moved to Nicole but the technical judgment did not.
A31: Quality | B31: Near-expiry batch disposition at the 30-day threshold | E31: R | F31: A | H31: -> | N31: C | U31: Product Development Specialist | V31: .claude/skills/batch-lifecycle-tracker/SKILL.md:71,94 | W31: Disposition is a quality gate, so it moves to Nicole. Posts back to inventory before any write-off.
A32: Quality | B32: Serious adverse event triage and recall kickoff (SKN-OPS-002, SKN-OPS-003) | C32: I | D32: I | E32: A/R | F32: C | N32: C | O32: C | V32: .claude/skills/complaint-and-event-handler/SKILL.md:85,89,95; .claude/skills/regulatory-manager/references/pedrero-contacts.md:9,13,21 | W32: The strictest gate in the suite: explicit approval at every step, §4.A through §4.F each a separate gate. Operator decides severity, team and whether external reporting is needed. A and R both AB. Stays with Alvin as Reg Lead, given the legal and agency exposure. Nicole consults. Pedrero Regulatory holds the binding external review; consult-only internally, with no Asana access and no internal authority, so the Reg Lead gate stays in-house.
A33: Quality | B33: SOP ratification, annual review and cross-cutting quality tasks | E33: R | F33: A | N33: C | V33: .claude/skills/quality-manager/SKILL.md:66,135; .claude/skills/quality-manager/references/sop-catalog.md:120; .claude/skills/quality-manager/references/qos-thresholds.md:52 | W33: QA Lead approves every ratification, review outcome, cross-cutting task and QoS threshold task. SOP §7 names a QA Manager for this; that seat is vacant and Perrine is filling it. Gate moved to Nicole per Leadership Business Review 2026-07-30 25:18-25:50.
A34: Quality | B34: Quality dashboard publish to the landing hub | E34: R | F34: A | H34: -> | N34: C | U34: Product Development Specialist | V34: .claude/skills/quality-status-reporter/SKILL.md:78 | W34: Operator approves the commit before push. Never commit without confirmation. A and R both AB. Nicole gates the content; Alvin retains the publish mechanics. Per Leadership Business Review 2026-07-30 26:02-26:17.
A35: Quality | B35: Final quality check on product and documentation across every function | C35: I | D35: I | E35: C | F35: A/R | I35: C | K35: C | N35: C | V35: Leadership Business Review 2026-07-30 25:35-26:01 | W35: The new cross-function gate. Verbatim: "anything related to quality of service or quality of product will go through Nicole's eyes as sort of that final quality check... Even with each function having or being the primary owner, we'll still have that quality gate." A and R both NI.
A36: Quality | B36: Quality management system framework and monthly quality-trend review | D36: I | E36: A | F36: R | N36: C | V36: Leadership Business Review 2026-07-30 25:18-26:17 | W36: Alvin owns the overall framework; Nicole runs it. Monthly trend review so recurring issues (the pump issue was the worked example) can drive packaging or formula decisions. Target: implemented by end of Q3.
A37: Regulatory & Compliance | B37: Pre-launch ingredient list review gate (SKN-OPS-008) | E37: A/R | F37: I | H37: -> | N37: C | O37: C | U37: Product Development Specialist | V37: .claude/skills/claims-il-and-label-keeper/SKILL.md:50; .claude/skills/claims-il-and-label-keeper/references/il-claims-label-procedure.md:62; .claude/skills/regulatory-manager/references/pedrero-contacts.md:9,13,21 | W37: Operator approves intake. Reg Lead is the same person at v6.6, so the gate fires twice against one person. Pedrero holds the binding external call. A and R both AB. Pedrero Regulatory holds the binding external review; consult-only internally, with no Asana access and no internal authority, so the Reg Lead gate stays in-house.
A38: Regulatory & Compliance | B38: Pedrero engagement and send approval | E38: A/R | N38: C | O38: C | V38: .claude/skills/claims-il-and-label-keeper/SKILL.md:60; .claude/skills/regulatory-manager/SKILL.md:140; .claude/skills/regulatory-manager/references/pedrero-contacts.md:9,13,21 | W38: Reg Lead approves every Pedrero send; Operator hits send manually. Both roles are Alvin. A and R both AB. Pedrero Regulatory holds the binding external review; consult-only internally, with no Asana access and no internal authority, so the Reg Lead gate stays in-house.
A39: Regulatory & Compliance | B39: Claim substantiation and new-claim defensibility | C39: C | D39: I | E39: A/R | H39: -> | I39: C | K39: C | N39: C | O39: C | U39: Product Development Specialist | V39: .claude/skills/claims-il-and-label-keeper/SKILL.md:97; .claude/skills/claims-il-and-label-keeper/references/il-claims-label-procedure.md:29; Alvin, 2026-07-31 (role correction); .claude/skills/regulatory-manager/references/pedrero-contacts.md:9,13,21 | W39: Operator approves the path; Reg Lead approves the Pedrero stage. The procedure exists because new claims from marketing or the founder used to skip Pedrero sign-off. A and R both AB. The procedure exists because new claims from marketing or the founder used to skip Pedrero sign-off, so both are consulted rather than bypassed. Pedrero Regulatory holds the binding external review; consult-only internally, with no Asana access and no internal authority, so the Reg Lead gate stays in-house.
A40: Regulatory & Compliance | B40: Label artwork archive, IL cross-check and label-law checks (Pantone, Canada, Quebec, 19-state toxics) | C40: C | D40: I | E40: R | F40: C | K40: A | M40: C | N40: C | O40: C | V40: .claude/skills/claims-il-and-label-keeper/SKILL.md:85; .claude/skills/claims-il-and-label-keeper/references/il-claims-label-procedure.md:93; Alvin, 2026-07-31 (role correction); .claude/skills/regulatory-manager/references/pedrero-contacts.md:9,13,21 | W40: Operator approves each pass outcome; Reg Lead approves any archive entry. Creative produces the artwork under review. Erin answers for the artwork being right as lead technical authority. Alvin runs the IL cross-check and the label-law passes and holds the Reg Lead gate on archive entries, so the regulatory approval and the artwork authority are separate people. Pedrero Regulatory holds the binding external review; consult-only internally, with no Asana access and no internal authority, so the Reg Lead gate stays in-house.
A41: Regulatory & Compliance | B41: Reformulation claim bridge when a SKU reformulates without QIL parity | E41: A | F41: C | N41: R | O41: C | V41: .claude/skills/claims-il-and-label-keeper/references/il-claims-label-procedure.md:281; .claude/skills/regulatory-manager/references/pedrero-contacts.md:9,13,21 | W41: Reg Lead approves the QIL recovery ask to the prior manufacturer; PD Lead does the formulation work. Pedrero Regulatory holds the binding external review; consult-only internally, with no Asana access and no internal authority, so the Reg Lead gate stays in-house.
A42: Regulatory & Compliance | B42: Retailer attestation responses (Sephora, Ulta, Whole Foods, Credo) | C42: C | D42: I | E42: A/R | F42: C | H42: -> | N42: C | O42: C | U42: Product Development Specialist | V42: .claude/skills/claims-il-and-label-keeper/SKILL.md:105; .claude/skills/regulatory-manager/SKILL.md:122; Alvin, 2026-07-31 (role correction); .claude/skills/regulatory-manager/references/pedrero-contacts.md:9,13,21 | W42: Reg Lead approves the retailer submission after Pedrero approval. Voice of Customer consults where customer-perceived attributes matter. A and R both AB. Ayesha consulted - retailer clean-standard positioning is a brand claim. Pedrero Regulatory holds the binding external review; consult-only internally, with no Asana access and no internal authority, so the Reg Lead gate stays in-house.
A43: Regulatory & Compliance | B43: MoCRA registrations, state filings and Leaping Bunny renewal | E43: A/R | H43: -> | I43: I | N43: I | O43: C | U43: Product Development Specialist | V43: .claude/skills/regulatory-manager/SKILL.md:114,367; .claude/skills/regulatory-manager/references/pedrero-contacts.md:9,13,21 | W43: Operator approves the filing draft; Reg Lead approves every registration record write. Both roles are Alvin. A and R both AB. Pedrero Regulatory holds the binding external review; consult-only internally, with no Asana access and no internal authority, so the Reg Lead gate stays in-house.
A44: Regulatory & Compliance | B44: SAE and recall agency filings, including the 15-day MoCRA clock (SKN-OPS-009) | C44: I | D44: I | E44: A/R | F44: C | N44: C | O44: C | V44: .claude/skills/adverse-event-and-recall-reporter/SKILL.md:65,108; .claude/skills/regulatory-manager/references/pedrero-contacts.md:9,13,21 | W44: Two distinct gates per filing - Pedrero send approval and agency submission approval - both held by Alvin. Statutory clock with no named backup. A and R both AB. Pedrero Regulatory holds the binding external review; consult-only internally, with no Asana access and no internal authority, so the Reg Lead gate stays in-house.
A45: Regulatory & Compliance | B45: Regulatory fan-out routing and the regulatory dashboard publish | E45: A/R | F45: I | N45: C | O45: C | V45: .claude/skills/regulatory-manager/SKILL.md:60; .claude/skills/regulatory-status-reporter/SKILL.md:90; .claude/skills/regulatory-manager/references/pedrero-contacts.md:9,13,21 | W45: Two gates per fan-out (Operator for the routing call, Reg Lead for task creation), both Alvin. Operator approves the dashboard commit before push. A and R both AB. Pedrero Regulatory holds the binding external review; consult-only internally, with no Asana access and no internal authority, so the Reg Lead gate stays in-house.
A46: Regulatory & Compliance | B46: Pedrero engagement letter, scope and renewal | D46: C | E46: A/R | F46: I | O46: C | V46: .claude/skills/regulatory-manager/references/pedrero-contacts.md:50; Alvin, 2026-07-31 (external partners) | W46: The engagement letter governs scope, retainer, response windows and dispute resolution. Annual renewal. A and R both AB - the only person managing the regulatory partner relationship.
A47: Retail & Wholesale | B47: Retailer and reseller first contact | D47: I | E47: C | F47: A/R | V47: .claude/skills/purchasing-manager/SKILL.md:55; acb-thelanding: data/links.json | W47: First-contact owner for retailer, promotional_goods and accessories vendor types is the Sr. Director Consumer Strategy & Ops. A and R both NI. Consistent with Nicole's all-channel accountability.
A48: Retail & Wholesale | B48: Retail channel launch programs: UBM cohort positioning, price ladder, Amazon Vendor | D48: I | E48: R | F48: A | I48: C | V48: .claude/skills/purchasing-manager/SKILL.md:55; .claude/skills/sjs-retail-intel/SKILL.md:52; .claude/skills/logistics-manager/SKILL.md:80; acb-thelanding: data/links.json; Alvin, 2026-07-31 (marketing, wholesale and web) | W48: UBM launch June 2026. Nicole holds the channel relationship; Alvin runs the positioning and outbound work. Hub lists wholesale as "Owned by TBD" (links.json, Sales & Commerce lead). Resolved to Nicole as part of all-channel accountability.
A49: Retail & Wholesale | B49: Wholesale pipeline and new retail partner development | C49: I | D49: I | E49: C | F49: A/R | I49: C | V49: acb-thelanding: data/links.json (Sales & Commerce lead: "TBD (wholesale)"); Alvin, 2026-07-31 (marketing, wholesale and web) | W49: Hub left wholesale unowned. Resolved to Nicole with all-channel accountability. A and R both Nicole - no second pair of eyes on new-partner decisions.
A50: Retail & Wholesale | B50: Retail price architecture and the pricing matrix | C50: I | D50: C | E50: R | F50: A | I50: C | N50: C | V50: acb-thelanding: data/links.json (Sales & Commerce / Retail Price Architecture, SJS Pricing Matrix); Alvin, 2026-07-31 (marketing, wholesale and web) | W50: Live pricing matrix on the hub carries retail, wholesale and subscription prices with margin colouring. Ties to the margin framework, so Danielle consulted as the walk-away approver.
A51: Retail & Wholesale | B51: Retailer promo calendar (Sephora, Ulta) and promo planning | C51: I | D51: I | E51: C | F51: A | I51: R | J51: C | V51: acb-thelanding: data/links.json (Market Intelligence / Promo Landscape); Alvin, 2026-07-31 (marketing, wholesale and web) | W51: Promo Landscape tracks the Sephora and Ulta promo calendar. Marketing runs the planning; Nicole answers for the channel commitment.
A52: Marketing & Brand | B52: Quarterly competitive teardowns across the five comp brands | C52: I | D52: C | E52: I | F52: C | I52: A/R | J52: C | V52: .claude/skills/sjs-comp-intel/references/team-ownership.md:19,23-30; Alvin, 2026-07-31 (role correction) | W52: Soraya owns teardown production and comp brand profile maintenance. A and R both SS. Danielle consulted rather than only receiving the finished teardown.
A53: Marketing & Brand | B53: Quarterly teardown sign-off before circulation | D53: I | E53: A | F53: C | I53: R | V53: .claude/skills/sjs-comp-intel/references/team-ownership.md:65; .claude/skills/sjs-comp-intel/SKILL.md:50 | W53: Alvin signs off before it circulates to Danielle and the SJS brand team.
A54: Marketing & Brand | B54: Monthly competitive trend digest and cross-stream signal routing | C54: I | D54: C | E54: I | F54: A/R | I54: C | J54: C | V54: .claude/skills/sjs-comp-intel/references/team-ownership.md:3,9-15; Alvin, 2026-07-31 (role correction) | W54: Stream DRI owns digest production and the 'what it means for SJS' analytical layer. Named as the stream's heartbeat - first thing protected under capacity pressure. A and R both NI. Danielle consulted on the digest's read.
A55: Marketing & Brand | B55: Social listening and comp brand monitoring (TikTok, IG, Pinterest, retailer new arrivals) | C55: I | D55: C | I55: C | J55: A/R | V55: .claude/skills/sjs-comp-intel/references/team-ownership.md:34,40-44; Alvin, 2026-07-31 (role correction) | W55: Kate owns social listening tool maintenance, query hygiene and the weekly retailer new-arrivals scan. A and R both KL. Danielle consulted on what the social signal implies for brand.
A56: Marketing & Brand | B56: Brand guideline custody (fonts, colors, logos, voice) | C56: C | D56: A | I56: C | J56: I | K56: R | L56: C | V56: .claude/skills/sweet-july-skin-brand/SKILL.md:1; references/architecture/system_map.md:157; Alvin, 2026-07-31 (role correction); acb-thelanding: data/links.json | W56: Every output-producing skill defers here for canonical brand spec; no skill carries its own copy. President answers for brand custody; Creative Director maintains it. Ayesha consulted - the brand carries her name. Every output-producing skill defers here for canonical spec. Hub lists Brand & Creative as "Owned by Soraya" as function lead; custody accountability sits with the President per the 31 July correction. Both hold: Soraya runs the function, Danielle answers for the brand standard.
A57: Marketing & Brand | B57: Annual team holiday communications (11 sends across 3 templates) | D57: I | E57: A/R | F57: I | I57: I | J57: I | L57: I | V57: .claude/skills/ac-brands-holiday-comms/SKILL.md:26,165 | W57: Sends from alvin@ac-brands.com with the team on BCC. Includes the Outlook calendar sync and annual maintenance. A and R both AB.
A58: Marketing & Brand | B58: Weekly founder briefing, Slides 5 and 6 | C58: I | D58: I | E58: A/R | F58: C | N58: C | V58: .claude/skills/ayesha-weekly-briefing/SKILL.md:49,72 | W58: Alvin owns both Slide 5 (Business Operations) and Slide 6 PD-Ops content; Nicole co-authors Slide 6 with her core PD content. A and R both AB.
A59: Marketing & Brand | B59: Operational special projects: labels, PR seeding, sampling | C59: I | D59: C | E59: R | F59: A | G59: -> | I59: C | J59: C | K59: C | U59: Operations Specialist | V59: SharePoint: Sweet July Skin - Operations Specialist - Job Description.docx; Email to Danielle 2026-07-27 'Proposed Ops Positions'; Alvin, 2026-07-31 (role correction) | W59: Named in the Ops Specialist JD, and in the email as making sure product is where it needs to be for launches, promos, PR seeding and sampling. Danielle consulted - PR seeding and sampling are brand-facing.
A60: Marketing & Brand | B60: Campaign direction and seasonal brand moments | C60: C | D60: A | E60: I | F60: C | I60: R | J60: C | K60: C | V60: Alvin, 2026-07-31 (role correction); .claude/skills/sjs-margin-walk-away/SKILL.md:93 | W60: Added 2026-07-31. Campaign direction was absent from the matrix, which is why the President and the Founder had almost no Marketing presence. Danielle answers for it - Soraya reports to her and the margin sources already have her approving every repricing and channel call. Ayesha consulted on brand moments.
A61: Marketing & Brand | B61: Editorial and content calendar | C61: I | D61: C | E61: I | F61: C | I61: A | J61: R | K61: C | V61: acb-thelanding: data/links.json (Marketing / Owned Channels); Alvin, 2026-07-31 (marketing, wholesale and web) | W61: Hub lists Marketing as "Owned by TBD"; resolved to Soraya as Marketing Manager. Editorial Calendar is a named tool under Owned Channels.
A62: Marketing & Brand | B62: Email marketing: Klaviyo flows and campaign sends | C62: I | D62: C | E62: I | F62: C | I62: A | J62: C | R62: R | V62: acb-thelanding: data/links.json (Marketing / Klaviyo Performance); Alvin, 2026-07-31 (marketing, wholesale and web) | W62: WITHIN runs most of our digital marketing including email execution. Soraya answers for the channel. Klaviyo Performance is a named tool on the hub.
A63: Marketing & Brand | B63: Paid media: Meta, Google and channel spend | C63: I | D63: C | E63: C | F63: C | I63: A | R63: R | V63: acb-thelanding: data/links.json (Marketing / Paid Media Dashboard); Alvin, 2026-07-31 (marketing, wholesale and web) | W63: WITHIN is the digital marketing agency and runs paid execution. Alvin consulted on spend against margin floors. Quarterly business reviews with WITHIN - the most recent was 20 July.
A64: Marketing & Brand | B64: Social media content and publishing | C64: I | D64: C | I64: A | J64: R | K64: C | L64: C | V64: acb-thelanding: data/links.json (Marketing / Social Media Dashboard); Alvin, 2026-07-31 (marketing, wholesale and web) | W64: Distinct from social listening, which Kate is accountable for. Here she does the publishing work and Soraya answers for the channel.
A65: Marketing & Brand | B65: Influencer and earned media programs | C65: I | D65: C | E65: I | F65: C | I65: A | J65: R | V65: acb-thelanding: data/links.json; Alvin, 2026-07-31 (marketing, wholesale and web) | W65: Brand-facing and founder-adjacent, so Danielle consulted and Ayesha informed. The physical seeding logistics sit on the Operations special-projects row.
A66: Marketing & Brand | B66: WITHIN agency relationship and quarterly business reviews | C66: I | D66: C | E66: C | F66: C | I66: A/R | V66: Alvin, 2026-07-31 (marketing, wholesale and web) | W66: A and R both Soraya. WITHIN holds most of our digital marketing execution, so the engagement is a single point of dependency - same shape as the other five external parties.
A67: Creative | B67: Creative direction on packaging, artwork and brand visuals | C67: C | D67: C | E67: I | I67: C | K67: A/R | L67: C | V67: .claude/skills/asana-pd-manager/references/role-map.md:22; Alvin, 2026-07-31 (role correction) | W67: Creative Director owns packaging, artwork and brand visuals. A and R both EH. Creative Director owns the direction as lead technical authority, and is a contractor. Danielle and Ayesha both consulted. A and R the same person - no second pair of eyes, and no internal backup either.
A68: Creative | B68: Packaging and artwork execution | C68: I | D68: I | E68: I | K68: A | L68: C | M68: R | N68: C | V68: .claude/skills/asana-pd-manager/references/role-map.md:23; .claude/skills/sjs-comp-intel/references/team-ownership.md:79; Alvin, 2026-07-31 (role correction) | W68: Jan is the creative contractor under Erin. Title differs between sources - Packaging Engineer in one, creative contractor in the other. Erin holds technical authority; Jan executes. Both contractors.
A69: Creative | B69: Creative Requests intake and design coordination | D69: C | E69: I | I69: C | K69: C | L69: A/R | V69: .claude/skills/sjs-status-reporter/SKILL.md:352; .claude/skills/asana-pd-manager/references/role-map.md:24; Alvin, 2026-07-31 (role correction) | W69: Creative Requests Asana project owner is Ivy, Editorial/Design team. Ivy supports Erin and Jan. A and R both IT. Danielle consulted on intake priority.
A70: Ecommerce & DTC | B70: Shopify revenue and channel position read | D70: I | E70: R | F70: A | I70: C | V70: connections.md:7; context/about-business.md:5; acb-thelanding: data/links.json; Alvin, 2026-07-31 (marketing, wholesale and web) | W70: Nicole is accountable for all channels - DTC, Amazon and wholesale - with Alvin consulted and Danielle informed. This was the last row on the matrix with no owner; it now has one.
A71: Ecommerce & DTC | B71: Daily DTC fulfillment KPIs and the SJ Shipping Dashboard | E71: C | F71: A/R | G71: -> | U71: Operations Specialist | V71: .claude/skills/oc3pl-order-manager/SKILL.md:61,191; .claude/skills/ayesha-weekly-briefing/SKILL.md:123 | W71: Ex-Ops-Coordinator scope, now Nicole per the interim split. A and R both NI.
A72: Ecommerce & DTC | B72: Channel operations and promo setup across DTC, UBM and Amazon | D72: I | E72: R | F72: A | G72: -> | I72: C | J72: C | U72: Operations Specialist | V72: SharePoint: Sweet July Skin - Operations Specialist - Job Description.docx; acb-thelanding: data/links.json; Alvin, 2026-07-31 (marketing, wholesale and web) | W72: Named in the Ops Specialist JD under Order Management & Channel Operations. Nicole holds the channel relationship. Part of Nicole's all-channel accountability.
A73: Ecommerce & DTC | B73: Proactive reships and fulfillment-issue resolution | E73: C | F73: A/R | G73: -> | U73: Operations Specialist | V73: SharePoint: Sweet July Skin - Operations Specialist - Job Description.docx | W73: JD wording: resolve fulfillment issues "before a customer has to follow up." Sits inside Nicole's interim OC3PL coverage. A and R both NI.
A74: Ecommerce & DTC | B74: Amazon channel management (FBA, AWD, Seller Central) | C74: I | D74: I | E74: R | F74: A | G74: -> | I74: C | U74: Operations Specialist | V74: acb-thelanding: data/links.json (Sales & Commerce / Amazon Dashboard); Alvin, 2026-07-31 (marketing, wholesale and web) | W74: Hub gave Amazon to Alvin; resolved to Nicole under all-channel accountability with Alvin doing the work. Inventory and inbound pipeline transition to the Ops Specialist.
A75: Ecommerce & DTC | B75: Product detail page content and product copy | D75: I | E75: I | F75: C | I75: A/R | K75: C | L75: C | N75: C | V75: acb-thelanding: data/links.json (Sales & Commerce / SJS Product Copy Database); Alvin, 2026-07-31 (marketing, wholesale and web) | W75: Product Copy Database is live from PLM and carries every claim, ingredient line, FAQ and Amazon title across DTC, Amazon and wholesale. Perrine and Regulatory consulted because claims on a PDP are claims. A and R both Soraya.
A76: Finance | B76: Margin architecture framework and quarterly portfolio review | D76: C | E76: A/R | F76: C | V76: .claude/skills/sjs-margin-architect/references/framework.md:209; .claude/skills/sjs-margin-portfolio-review/SKILL.md:1 | W76: Framework reference plus the quarterly portfolio sweep and traffic-light report. A and R both AB.
A77: Finance | B77: Per-SKU margin pressure-test against channel floors | D77: I | E77: R | F77: C | I77: C | N77: A | V77: .claude/skills/sjs-margin-pressure-test/SKILL.md:93 | W77: Flagged as Perrine and Soraya's call to ratify, with Alvin on admin, Nicole consulting and Danielle approving.
A78: Finance | B78: Walk-away decision when a SKU breaks its channel floor | D78: A | E78: R | F78: C | I78: C | N78: C | V78: .claude/skills/sjs-margin-walk-away/SKILL.md:93,105,118 | W78: Danielle approves on three of the four paths. Alvin carries the work on all four.
A79: Finance | B79: SKU archetype and Standard / Acquisition designation | D79: I | E79: R | F79: C | N79: A | V79: .claude/skills/sjs-margin-walk-away/SKILL.md:78 | W79: Perrine as PD owner with Alvin on PD admin and sourcing; Nicole consults.
A80: Finance | B80: Monthly and quarterly vendor cost rollups | D80: I | E80: A/R | P80: C | V80: .claude/skills/regulatory-manager/SKILL.md:196; .claude/skills/purchasing-manager/SKILL.md:365; Alvin, 2026-07-31 (external partners) | W80: regulatory-manager Jobs 8 and 9 read vendor_invoices directly; purchasing-manager has no rollup of its own. A and R both AB. Ironclad consulted - the rollup feeds their books.
A81: Finance | B81: Accounts payable, bookkeeping and payroll | D81: C | E81: A | P81: R | V81: Alvin, 2026-07-31 (external partners) | W81: Ironclad Finance runs AP, bookkeeping and payroll; Dan Bender is the contact. Cost-side accountability sits with Operations because the vendor-invoice pipeline and its five approval gates feed it. No longer an unowned function.
A82: Finance | B82: Month-end close and management reporting | C82: I | D82: A | E82: C | F82: C | P82: R | V82: Alvin, 2026-07-31 (external partners) | W82: Ironclad Finance closes the books and produces the reporting; Dan Bender is the contact. Reporting accountability sits with the President.
A83: Finance | B83: Annual budget and forecast consolidation | C83: I | D83: A | E83: C | F83: C | I83: C | P83: R | V83: Alvin, 2026-07-31 (external partners) | W83: President answers for the budget. Operations and Consumer Strategy feed the operating and channel assumptions.
A84: Finance | B84: Inventory valuation and cost of goods | D84: I | E84: A | F84: C | N84: C | P84: R | V84: Alvin, 2026-07-31 (external partners); .claude/skills/inventory-manager/SKILL.md:18 | W84: Cost side, so accountability sits with Operations - it flows out of purchasing, receiving and the inventory ledger. Ironclad carries it into the books.
A85: People & Admin | B85: Hiring the Operations Specialist and the PD Project Manager Specialist | C85: I | D85: C | E85: A | F85: R | Q85: C | V85: decisions/log.md:52,58; context/priorities.md:3; Alvin, 2026-07-31 (external partners) | W85: Both new roles report to Nicole. Decision owner recorded as Alvin, with Nicole on the two new roles once filled. Priority 1 of 2 this quarter. Calm HR runs the recruiting process once the RACI clears Danielle.
A86: People & Admin | B86: Tool procurement, vendor renewals and shared-folder admin | E86: A/R | F86: C | L86: C | V86: .claude/skills/sjs-comp-intel/references/team-ownership.md:50; .claude/skills/sjs-comp-intel/references/sequencing-plan.md:12 | W86: Ex-Ops-Coordinator scope. Alvin carries it directly until the Operations Specialist starts. A and R both AB.
A87: People & Admin | B87: Employee onboarding, offboarding and access deprovisioning | D87: C | E87: A | F87: C | Q87: R | T87: C | V87: .claude/skills/asana-pd-manager/references/role-map.md:48-56; Alvin, 2026-07-31 (external partners); Alvin, 2026-07-31 (Coastal Interactive; PD visibility) | W87: Calm HR is the PEO and co-employer and runs the process; Alvin is the liaison and answers for it. Danielle consulted. No longer an unowned function - the departed-role-holder checklist in the PD role-map remains the internal system-side counterpart. Two partners split this: Calm HR runs the employment side, Coastal Interactive runs equipment and account provisioning. Alvin is the liaison to both and answers for the whole.
A88: People & Admin | B88: Operations Specialist recruiting | C88: I | D88: C | E88: A | F88: R | V88: Leadership Business Review 2026-07-30 52:48-53:17; Email to Danielle 2026-07-27 'Proposed Ops Positions' | W88: Prioritized first. Danielle: "we're going to prioritize the operations... Specialist." Reports to Nicole. Target in place before Q4. Salary band $72-90K.
A89: People & Admin | B89: PD Specialist role definition and phased recruiting | C89: I | D89: C | E89: A | F89: R | V89: Leadership Business Review 2026-07-30 53:17-57:10; Email to Danielle 2026-07-27 'Proposed Ops Positions' | W89: Phased in after the Ops Specialist. Danielle scopes it as "air traffic control, holding people accountable" rather than strategy or ideation, and is adding trend-forecasting language to the JD. Reports to Nicole. Salary band $75-95K.
A90: People & Admin | B90: SOP cleanup and operational prep before new-hire onboarding | D90: I | E90: A | F90: R | V90: Leadership Business Review 2026-07-30 54:24-55:43, 1:00:32 | W90: Danielle's condition on the hire: clean up the system first so the role can function. Nicole's action item from the review.
A91: People & Admin | B91: Employee handbook and HR policy | C91: I | D91: C | E91: A | F91: I | Q91: R | V91: Alvin, 2026-07-31 (external partners) | W91: Calm HR drafts and maintains; Alvin is the liaison and answers for it; Danielle co-approves. Handbook is in flight as of 2026-07-30 and goes to legal review before implementation.
A92: People & Admin | B92: Benefits administration and payroll processing | D92: C | E92: A | P92: C | Q92: R | V92: Alvin, 2026-07-31 (external partners) | W92: Calm HR administers as co-employer. Ironclad consulted where payroll hits the books.
A93: People & Admin | B93: Employment compliance and separations | D93: C | E93: A | Q93: R | V93: Alvin, 2026-07-31 (external partners) | W93: Calm HR runs the process with outside counsel where needed. Danielle co-approves every separation.
A94: IT / Systems & Data | B94: PLM schema, write path, audit log and Supabase wiki custody | E94: A/R | N94: C | V94: .claude/skills/plm-assistant/SKILL.md:292; decisions/wiki-layer-audit-2026-07-29.md:52 | W94: plm-assistant is the sole PLM writer and every write needs Operations sign-off. Job 0 wiki write-back has not fired since 2026-05-26. A and R both AB.
A95: IT / Systems & Data | B95: Landing hub publish and Netlify Function maintenance | E95: A/R | V95: .claude/skills/quality-status-reporter/SKILL.md:34-50; .claude/skills/quality-status-reporter/references/hub-integration.md:85 | W95: All hub writes go through the landing-hub-publish Function behind an Operator gate. Deploy is commit-and-push only, never Netlify CLI. A and R both AB.
A96: IT / Systems & Data | B96: Asana project, section, custom-field and connector configuration | E96: A/R | F96: C | T96: C | V96: references/architecture/asana_task_contract.md:227; connections.md:5-13; Alvin, 2026-07-31 (Coastal Interactive; PD visibility) | W96: An unresolvable role-holder is surfaced for Alvin to decide, not dropped. Seven tool domains registered; iMessage still not connected. A and R both AB. Coastal Interactive consulted on identity, access and integration plumbing behind the connectors.
A97: IT / Systems & Data | B97: Skill suite authorship, audit and versioning | E97: A/R | V97: decisions/skills-architecture-tracker.md:4; decisions/log.md:31,45 | W97: Owner recorded as Alvin Belt across the architecture decisions. Priority 2 of 2 this quarter. A and R both AB.
A98: IT / Systems & Data | B98: The 23 scheduled Routines and their HITL gates | E98: A/R | F98: I | V98: scheduled-prompts/weekly-pd-update.md:91; scheduled-prompts/sjs-purchasing-monthly-rollup-and-snapshot.md:79 | W98: Nothing commits until Alvin says go. Same pattern across all 23 Routines, including the ones that fire unattended on a schedule. A and R both AB.
A99: IT / Systems & Data | B99: RACI and role framework across Operations and PD | D99: C | E99: A | F99: R | V99: Leadership Business Review 2026-07-30 52:12-52:39 | W99: Alvin owns the framework, built with Nicole in the builder session, then to Danielle for final review before it goes to Calm HR to start recruiting.
A100: IT / Systems & Data | B100: Website platform, Shopify storefront and web releases | D100: A | E100: I | F100: C | I100: C | K100: C | L100: C | S100: R | V100: Alvin, 2026-07-31 (marketing, wholesale and web) | W100: Teknologics is the web development partner. Danielle accountable; Nicole is the systems and tech owner; Erin and Ivy on visual design; Soraya consulted on merchandising and content; Alvin informed.
...

Sheet Analysis
A1: Ownership concentration, coverage gaps, and what the two seats move
A3: Counts are live formulas over the RACI sheet, so they move if a row changes. Read against the matrix. Reflects the 30 July 2026 leadership review and the 31 July role corrections.
A5: Position and holder | B5: A | C5: R | D5: A/R | E5: Hands off | F5: Absorbs | G5: A after | H5: R after
A6: AC: Owner / Founder (Ayesha Curry) | B6: =COUNTIF(RACI!C3:C104,"A")+COUNTIF(RACI!C3:C104,"A/R") | C6: =COUNTIF(RACI!C3:C104,"R")+COUNTIF(RACI!C3:C104,"A/R") | D6: =COUNTIF(RACI!C3:C104,"A/R") | E6: 0 | F6: 0 | G6: =B6 | H6: =C6-E6+F6
A7: DI: President (Danielle Iturbe) | B7: =COUNTIF(RACI!D3:D104,"A")+COUNTIF(RACI!D3:D104,"A/R") | C7: =COUNTIF(RACI!D3:D104,"R")+COUNTIF(RACI!D3:D104,"A/R") | D7: =COUNTIF(RACI!D3:D104,"A/R") | E7: 0 | F7: 0 | G7: =B7 | H7: =C7-E7+F7
A8: AB: VP of Operations (Alvin Belt) | B8: =COUNTIF(RACI!E3:E104,"A")+COUNTIF(RACI!E3:E104,"A/R") | C8: =COUNTIF(RACI!E3:E104,"R")+COUNTIF(RACI!E3:E104,"A/R") | D8: =COUNTIF(RACI!E3:E104,"A/R") | E8: 30 | F8: 0 | G8: =B8 | H8: =C8-E8+F8
A9: NI: Sr. Director, Consumer Strategy & Operations (Nicole Iturbe) | B9: =COUNTIF(RACI!F3:F104,"A")+COUNTIF(RACI!F3:F104,"A/R") | C9: =COUNTIF(RACI!F3:F104,"R")+COUNTIF(RACI!F3:F104,"A/R") | D9: =COUNTIF(RACI!F3:F104,"A/R") | E9: 3 | F9: 0 | G9: =B9 | H9: =C9-E9+F9
A10: OPS: Operations Specialist (Open seat) | B10: =COUNTIF(RACI!G3:G104,"A")+COUNTIF(RACI!G3:G104,"A/R") | C10: =COUNTIF(RACI!G3:G104,"R")+COUNTIF(RACI!G3:G104,"A/R") | D10: =COUNTIF(RACI!G3:G104,"A/R") | E10: 0 | F10: 18 | G10: =B10 | H10: =C10-E10+F10
A11: PDS: Product Development Specialist (Open seat) | B11: =COUNTIF(RACI!H3:H104,"A")+COUNTIF(RACI!H3:H104,"A/R") | C11: =COUNTIF(RACI!H3:H104,"R")+COUNTIF(RACI!H3:H104,"A/R") | D11: =COUNTIF(RACI!H3:H104,"A/R") | E11: 0 | F11: 16 | G11: =B11 | H11: =C11-E11+F11
A12: SS: Marketing Manager (Soraya Salgadoe) | B12: =COUNTIF(RACI!I3:I104,"A")+COUNTIF(RACI!I3:I104,"A/R") | C12: =COUNTIF(RACI!I3:I104,"R")+COUNTIF(RACI!I3:I104,"A/R") | D12: =COUNTIF(RACI!I3:I104,"A/R") | E12: 0 | F12: 0 | G12: =B12 | H12: =C12-E12+F12
A13: KL: Social Media Coordinator (Kate Le) | B13: =COUNTIF(RACI!J3:J104,"A")+COUNTIF(RACI!J3:J104,"A/R") | C13: =COUNTIF(RACI!J3:J104,"R")+COUNTIF(RACI!J3:J104,"A/R") | D13: =COUNTIF(RACI!J3:J104,"A/R") | E13: 0 | F13: 0 | G13: =B13 | H13: =C13-E13+F13
A14: EH: Creative Director (Erin Hover) | B14: =COUNTIF(RACI!K3:K104,"A")+COUNTIF(RACI!K3:K104,"A/R") | C14: =COUNTIF(RACI!K3:K104,"R")+COUNTIF(RACI!K3:K104,"A/R") | D14: =COUNTIF(RACI!K3:K104,"A/R") | E14: 0 | F14: 0 | G14: =B14 | H14: =C14-E14+F14
A15: IT: Creative / Design Coordinator (Ivy Tan) | B15: =COUNTIF(RACI!L3:L104,"A")+COUNTIF(RACI!L3:L104,"A/R") | C15: =COUNTIF(RACI!L3:L104,"R")+COUNTIF(RACI!L3:L104,"A/R") | D15: =COUNTIF(RACI!L3:L104,"A/R") | E15: 0 | F15: 0 | G15: =B15 | H15: =C15-E15+F15
A16: JH: Packaging Engineer (Jan Haeck) | B16: =COUNTIF(RACI!M3:M104,"A")+COUNTIF(RACI!M3:M104,"A/R") | C16: =COUNTIF(RACI!M3:M104,"R")+COUNTIF(RACI!M3:M104,"A/R") | D16: =COUNTIF(RACI!M3:M104,"A/R") | E16: 0 | F16: 0 | G16: =B16 | H16: =C16-E16+F16
A17: PC: PD / R&D contractor, Milinyc (Perrine Calvet) | B17: =COUNTIF(RACI!N3:N104,"A")+COUNTIF(RACI!N3:N104,"A/R") | C17: =COUNTIF(RACI!N3:N104,"R")+COUNTIF(RACI!N3:N104,"A/R") | D17: =COUNTIF(RACI!N3:N104,"A/R") | E17: 0 | F17: 0 | G17: =B17 | H17: =C17-E17+F17
A18: PR: External regulatory partner (Pedrero Regulatory) | B18: =COUNTIF(RACI!O3:O104,"A")+COUNTIF(RACI!O3:O104,"A/R") | C18: =COUNTIF(RACI!O3:O104,"R")+COUNTIF(RACI!O3:O104,"A/R") | D18: =COUNTIF(RACI!O3:O104,"A/R") | E18: 0 | F18: 0 | G18: =B18 | H18: =C18-E18+F18
A19: IF: Outsourced finance (Dan Bender) (Ironclad Finance) | B19: =COUNTIF(RACI!P3:P104,"A")+COUNTIF(RACI!P3:P104,"A/R") | C19: =COUNTIF(RACI!P3:P104,"R")+COUNTIF(RACI!P3:P104,"A/R") | D19: =COUNTIF(RACI!P3:P104,"A/R") | E19: 0 | F19: 0 | G19: =B19 | H19: =C19-E19+F19
A20: CH: PEO and co-employer (Calm HR) | B20: =COUNTIF(RACI!Q3:Q104,"A")+COUNTIF(RACI!Q3:Q104,"A/R") | C20: =COUNTIF(RACI!Q3:Q104,"R")+COUNTIF(RACI!Q3:Q104,"A/R") | D20: =COUNTIF(RACI!Q3:Q104,"A/R") | E20: 0 | F20: 0 | G20: =B20 | H20: =C20-E20+F20
A21: WI: Digital marketing agency (WITHIN) | B21: =COUNTIF(RACI!R3:R104,"A")+COUNTIF(RACI!R3:R104,"A/R") | C21: =COUNTIF(RACI!R3:R104,"R")+COUNTIF(RACI!R3:R104,"A/R") | D21: =COUNTIF(RACI!R3:R104,"A/R") | E21: 0 | F21: 0 | G21: =B21 | H21: =C21-E21+F21
A22: TK: Web development (Teknologics) | B22: =COUNTIF(RACI!S3:S104,"A")+COUNTIF(RACI!S3:S104,"A/R") | C22: =COUNTIF(RACI!S3:S104,"R")+COUNTIF(RACI!S3:S104,"A/R") | D22: =COUNTIF(RACI!S3:S104,"A/R") | E22: 0 | F22: 0 | G22: =B22 | H22: =C22-E22+F22
A23: CI: Managed IT service provider (Coastal Interactive) | B23: =COUNTIF(RACI!T3:T104,"A")+COUNTIF(RACI!T3:T104,"A/R") | C23: =COUNTIF(RACI!T3:T104,"R")+COUNTIF(RACI!T3:T104,"A/R") | D23: =COUNTIF(RACI!T3:T104,"A/R") | E23: 1 | F23: 0 | G23: =B23 | H23: =C23-E23+F23
A24: Total activities | B24: =COUNTA(RACI!B3:B104)
A26: "A after" and "R after" project the book once both specialist seats are filled. Hands off counts rows where this position does the work today and an incoming seat takes it. Absorbs counts rows arriving on hire.
A28: Quality now has a gate, and it is not the VP
A30: The 30 July leadership review moved the quality function onto Nicole. Verbatim from the recording: "Nicole taking the primary focus on the quality management side of things with quality control... anything related to quality of service or quality of product will go through Nicole's eyes as sort of that final quality check... Even with each function having or being the primary owner, we'll still have that quality gate." That shows up as 10 of the 13 Quality rows accountable to Nicole, against 2 for Alvin and 1 for Perrine. Her total book of accountability goes from 8 rows to 21.
A32: Perrine moves to technical guidance
A34: She keeps A on the 7 rows where the judgment is genuinely formulation - formula stage-gate, compatibility and stability and RIPT and PET, in-market stability testing, reformulation, PD-linked receipt, and the two margin rows that turn on formulation cost. Packaging development moved to Erin Hover as the lead technical authority on packaging and artwork. She moves to consulted on everything process-shaped: NCR and CAPA lifecycle, batch hold and release, vendor quality flags, lab finding classification, SOP ratification. Danielle's framing in the review was that there were things the team had assumed Perrine would manage or organize that she is not, and that leadership can pull the plug even when she has submitted an approval. Splitting technical judgment from process ownership is what that means in practice.
A36: Three contractors hold accountability, and two of them hold it alone
A38: Erin Hover is the lead technical authority on packaging and artwork and is accountable for 4 rows - creative direction, packaging development, artwork execution, and the label artwork archive. She is also a contractor, and on creative direction she is both A and R with no internal counterpart. Jan Haeck, who executes under her, is a contractor too, so the whole packaging and artwork chain runs through people outside the company. Perrine Calvet is the third, accountable for 7 formulation rows. Between them that is 11 of 79 activities where nobody on staff can check the work or continue it. Neither specialist job description covers creative or formulation authority, so the two hires do not close this.
A40: Nobody is blank on a product decision
A42: Perrine and Soraya now hold a letter on all eight Product Development rows. Perrine was blank on one - founder brand-line approval - and Soraya was blank on all eight, which meant the marketing read had no formal visibility into any product decision. Both are Informed at minimum now. That is a small change with a real effect: a blank cell on a RACI is ambiguous in a way that Informed is not, because blank does not tell you whether the omission was deliberate.
A44: Marketing and the channels finally have owners with real activities under them
A46: Soraya goes from 1 accountable row to 8. Marketing now carries editorial calendar, Klaviyo email, paid media, social content, influencer and earned media, the WITHIN relationship, product copy and PDP content - none of which existed on the matrix before, because none of it has a skill behind it. Nicole goes from 21 to 26 with all-channel accountability plus wholesale pipeline, retail price architecture and the retailer promo calendar. Retail & Wholesale went from 2 rows to 5, Marketing from 9 to 15. A skill suite is a good source for what is automated; it is a poor source for what a business does.
A48: Where the President and the Founder sit
... A86: Perrine is an external contractor holding A on 8 rows with no internal counterpart, and one of those - compatibility and stability and RIPT and PET - has her as both A and R. Nobody inside AC Brands can check that work or continue it. Alvin is the other: the Operator gate has no alternate anywhere in the suite, and all 23 scheduled Routines stop at a human approval only he can clear. Succession is documented exactly once in the entire system, for competitive intelligence. Nothing comparable exists for the quality gate, the technical advisor, or the framework owner. That gap costs hours to close, not headcount, and it is the one I would fix first.

Sheet Gaps
A1: Type | B1: Function | C1: Gap | D1: Why it matters | E1: Owner / next step | F1: Est. hrs / month | G1: Source
A2: Open seat | B2: Operations & Supply Chain | C2: Operations Specialist. Approved, prioritized, recruiting now. Reports to Nicole. $72-90K. | D2: Alvin does the work on 11 of 12 Operations rows. This seat absorbs 16 activities across order ops, inventory, purchase-to-pay, freight and planning. | E2: Recruiting via Calm HR once the RACI clears Danielle | F2: 160 | G2: decisions/log.md:52; Leadership Business Review 2026-07-30 52:48-53:17; Ops Specialist JD
A3: Open seat | B3: Product Development | C3: PD Specialist. Approved, phased in after Ops. Reports to Nicole. $75-95K. | D3: Absorbs 16 activities including the whole quality-execution layer the JD calls 'run the quality system', plus document control and product regulatory work. Until then Nicole gates and Alvin executes. | E3: Define scope, then recruit after Ops seat lands | F3: 160 | G3: decisions/log.md:52; Leadership Business Review 2026-07-30 53:17-57:10; PD Specialist JD
A4: Resolved | B4: Finance | C4: Finance is owned. Ironclad Finance (Dan Bender) runs AP, bookkeeping, payroll, month-end close and reporting. Danielle accountable for reporting, Alvin for cost. | D4: Was flagged as unowned before the external partners were added to the matrix. The remaining question is not ownership but coverage: no internal finance headcount exists, so continuity depends on the Ironclad engagement. | E4: No action - confirm engagement terms and renewal date | F4: 0 | G4: Alvin, 2026-07-31 (external partners)
A5: Resolved | B5: People & Admin | C5: HR is owned. Calm HR is the PEO and co-employer and runs handbook, policy, benefits, payroll admin, onboarding, offboarding and separations. Alvin accountable as liaison, Danielle co-approves. | D5: Was flagged as unowned before the external partners were added. What remains internal is the system-side half of offboarding - Asana reassignment, wiki contact state, access deprovisioning - which the departed-role-holder checklist covers and which is still on Alvin. | E5: No action on HR; system-side offboarding to the Ops Specialist | F5: 4 | G5: Alvin, 2026-07-31 (external partners); asana-pd-manager/references/role-map.md:48-56
A6: Resolved | B6: Ecommerce & DTC | C6: Shopify revenue and channel position is owned. Nicole is accountable for all channels - DTC, Amazon and wholesale - with Alvin doing the work and Danielle informed. | D6: Was the last row on the matrix with no owner. The landing hub had split DTC and Amazon to Alvin and left wholesale as TBD; consolidating all channels under one accountability closes it. | E6: No action - every row on the matrix now has an owner | F6: 0 | G6: acb-thelanding: data/links.json; Alvin, 2026-07-31 (marketing, wholesale and web)
A7: Resolved | B7: Marketing & Brand | C7: Marketing is owned. Soraya is accountable across editorial, email, paid media and social. WITHIN responsible for paid and email execution, Kate for social content. | D7: The landing hub listed Marketing as "Owned by TBD" with four named tools and nobody against them. Fifteen Marketing rows now have an owner. | E7: No action - confirm WITHIN engagement terms and renewal | F7: 0 | G7: acb-thelanding: data/links.json; Alvin, 2026-07-31 (marketing, wholesale and web)
A8: Single point of failure | B8: Product Development | C8: Compatibility, stability, RIPT and PET decisions sit with an external contractor as both A and R. | D8: No internal counterpart can check the work or continue it. Pre-launch technical decisions have no second reader. | E8: PD Specialist as internal counterpart on hire | F8: 0 | G8: asana-pd-manager/references/role-map.md:16
A9: Concentration | B9: All functions | C9: Six whole functions run through external partner organisations: Regulatory (Pedrero), Finance (Ironclad), HR (Calm HR), digital marketing (WITHIN), web development (Teknologics), managed IT (Coastal Interactive). Plus three contractors on packaging, creative and formulation. | D9: Nine external parties hold the execution of Regulatory, Finance, HR, digital marketing, web development, managed IT, packaging, creative and formulation. Not a fault - it is how a team of nine covers this surface - but continuity rests on nine engagements rather than on employment, and each one is a renewal decision. Engagement terms are recorded for Pedrero only. | E9: Record engagement terms and renewal dates for all nine | F9: 0 | G9: Alvin, 2026-07-31 (external partners)
A10: Single point of failure | B10: Regulatory & Compliance | C10: Pedrero forms every regulatory opinion but holds no accountability, and Alvin performs every regulatory action. Consulted on 11 rows, responsible for none. | D10: Our own procedures make Pedrero consult-only with no Asana access and no internal authority, so the binding external call and the internal execution are both bottlenecks in different ways: their opinion gates the work, and only Alvin can act on it. | E10: Give the Reg Lead gate an alternate, or widen Pedrero's remit | F10: 0 | G10: regulatory-manager/references/pedrero-contacts.md:9,13,21
A11: Single point of failure | B11: Creative | C11: Erin Hover is a contractor and the lead technical authority on packaging and artwork, accountable for 4 rows with no internal backup. On creative direction she is both A and R. | D11: Jan Haeck executes under her and is also a contractor, so the entire packaging and artwork chain sits outside the company. Neither approved job description covers creative authority. | E11: Name an internal creative counterpart, or scope it into a future role | F11: 0 | G11: Alvin, 2026-07-31 (role correction); asana-pd-manager/references/role-map.md:22-23
A12: Single point of failure | B12: Quality | C12: Perrine holds A on 7 formulation rows as a contractor, with no named backup. | D12: Reduced from 11 by moving process gates to Nicole and packaging to Erin, which is real progress. What remains is genuinely formulation and genuinely single-threaded. | E12: Name a backup technical reviewer | F12: 0 | G12: Leadership Business Review 2026-07-30 25:18-25:50; quality-manager/references/role-map.md:14
A13: Single point of failure | B13: Regulatory & Compliance | C13: Operator and Reg Lead are the same person, so two gates designed to be independent fire against one approver. | D13: On ingredient-list packets, retailer attestations and FDA filings the second approval adds an audit entry but no second judgment. The 15-day reporting clock has no alternate. | E13: Split Reg Lead, or route the second gate to Pedrero | F13: 0 | G13: regulatory-manager/references/role-map.md:14; adverse-event-and-recall-reporter/SKILL.md:108
... A21: Uncovered brand | B21: All functions | C21: Sweet July, the lifestyle brand, has no coverage. The suite is Sweet July Skin plus company-wide work. | D21: Merch, licensing and non-skincare retail are run somewhere, but nothing documents who owns them. They cannot be put on a RACI from these sources. | E21: Danielle to confirm scope for the next version | F21: 0 | G21: references/architecture/system_map.md:3; context/about-business.md:3
A23: Hours per month | C23: Rough estimates. Open-seat rows are full-time-equivalent load, not incremental. Zero means the gap is a structural exposure rather than unbilled hours.
